{
  "db_name": "PostgreSQL",
  "query": "\n                SELECT id, user_id, token, action_type as \"action_type: ActionType\", used_at, expires_at, created_at, updated_at \n                FROM user_action_tokens WHERE token = $1 AND used_at IS NULL;\n            ",
  "describe": {
    "columns": [
      {
        "ordinal": 0,
        "name": "id",
        "type_info": "Uuid"
      },
      {
        "ordinal": 1,
        "name": "user_id",
        "type_info": "Uuid"
      },
      {
        "ordinal": 2,
        "name": "token",
        "type_info": "Varchar"
      },
      {
        "ordinal": 3,
        "name": "action_type: ActionType",
        "type_info": {
          "Custom": {
            "name": "action_type",
            "kind": {
              "Enum": [
                "verify-account",
                "reset-password"
              ]
            }
          }
        }
      },
      {
        "ordinal": 4,
        "name": "used_at",
        "type_info": "Timestamptz"
      },
      {
        "ordinal": 5,
        "name": "expires_at",
        "type_info": "Timestamptz"
      },
      {
        "ordinal": 6,
        "name": "created_at",
        "type_info": "Timestamptz"
      },
      {
        "ordinal": 7,
        "name": "updated_at",
        "type_info": "Timestamptz"
      }
    ],
    "parameters": {
      "Left": [
        "Text"
      ]
    },
    "nullable": [
      false,
      false,
      true,
      false,
      true,
      true,
      false,
      false
    ]
  },
  "hash": "b6126459540aefb9d41ed76774a8d0776d7d9aa345c18e8f842a43a5cd92ceb5"
}
